iso_financial_mcp/__init__.py
iso_financial_mcp/__main__.py
iso_financial_mcp/main.py
iso_financial_mcp/meta_tools.py
iso_financial_mcp/run_mcp.py
iso_financial_mcp/server.py
iso_financial_mcp/datasources/__init__.py
iso_financial_mcp/datasources/earnings_source.py
iso_financial_mcp/datasources/earnings_source_manager.py
iso_financial_mcp/datasources/finra_source.py
iso_financial_mcp/datasources/news_source.py
iso_financial_mcp/datasources/sec_rss_source.py
iso_financial_mcp/datasources/sec_source.py
iso_financial_mcp/datasources/sec_source_manager.py
iso_financial_mcp/datasources/sec_xbrl_source.py
iso_financial_mcp/datasources/trends_source.py
iso_financial_mcp/datasources/trends_source_manager.py
iso_financial_mcp/datasources/validation.py
iso_financial_mcp/datasources/yfinance_source.py
iso_financial_mcp/reliability/__init__.py
iso_financial_mcp/reliability/adaptive_rate_limiter.py
iso_financial_mcp/reliability/cache_layer.py
iso_financial_mcp/reliability/config_loader.py
iso_financial_mcp/reliability/configuration_manager.py
iso_financial_mcp/reliability/data_manager.py
iso_financial_mcp/reliability/default_config.yaml
iso_financial_mcp/reliability/error_handler.py
iso_financial_mcp/reliability/health_monitor.py
iso_financial_mcp/reliability/models.py
iso_financial_mcp/reliability/source_router.py
iso_financial_mcp-0.4.1.dist-info/METADATA
iso_financial_mcp-0.4.1.dist-info/WHEEL
iso_financial_mcp-0.4.1.dist-info/entry_points.txt
iso_financial_mcp-0.4.1.dist-info/licenses/LICENSE
iso_financial_mcp-0.4.1.dist-info/RECORD
