Metadata-Version: 2.4
Name: iso-financial-mcp
Version: 0.4.1
Summary: Enhanced MCP server providing comprehensive financial market data endpoints for quantitative trading opportunity detection and analysis
Project-URL: Homepage, https://github.com/Niels-8/isofinancial-mcp
Project-URL: Repository, https://github.com/Niels-8/isofinancial-mcp
Project-URL: Documentation, https://github.com/Niels-8/isofinancial-mcp#readme
Project-URL: Issues, https://github.com/Niels-8/isofinancial-mcp/issues
Project-URL: Bug Tracker, https://github.com/Niels-8/isofinancial-mcp/issues
Author: Niels-8
License: MIT License
License-File: LICENSE
Keywords: ai-trading,earnings,finance,finra,market-data,mcp,model-context-protocol,options,quantitative-analysis,sec-filings,short-squeeze,stocks,trading
Classifier: Development Status :: 4 - Beta
Classifier: Intended Audience :: Developers
Classifier: Intended Audience :: Financial and Insurance Industry
Classifier: License :: OSI Approved :: MIT License
Classifier: Operating System :: OS Independent
Classifier: Programming Language :: Python :: 3
Classifier: Programming Language :: Python :: 3.10
Classifier: Programming Language :: Python :: 3.11
Classifier: Programming Language :: Python :: 3.12
Classifier: Programming Language :: Python :: 3.13
Classifier: Topic :: Internet :: WWW/HTTP :: HTTP Servers
Classifier: Topic :: Office/Business :: Financial
Classifier: Topic :: Software Development :: Libraries :: Python Modules
Requires-Python: >=3.10
Requires-Dist: aiofiles>=24.1.0
Requires-Dist: aiohttp>=3.9.0
Requires-Dist: asyncio-throttle>=1.0.2
Requires-Dist: autogen-ext[mcp]>=0.7.4
Requires-Dist: beautifulsoup4>=4.12.0
Requires-Dist: build>=1.2.2.post1
Requires-Dist: cachetools>=5.3.0
Requires-Dist: fastmcp>=0.2.0
Requires-Dist: feedparser>=6.0.0
Requires-Dist: httpx>=0.27.0
Requires-Dist: lxml>=5.2.0
Requires-Dist: numpy>=1.26.0
Requires-Dist: pandas>=2.2.0
Requires-Dist: python-dotenv>=1.0.0
Requires-Dist: pytrends>=4.9.0
Requires-Dist: pyyaml>=6.0.0
Requires-Dist: twine>=6.1.0
Requires-Dist: uvicorn>=0.30.0
Requires-Dist: yfinance>=0.2.28
Provides-Extra: dev
Requires-Dist: black>=24.0.0; extra == 'dev'
Requires-Dist: mypy>=1.10.0; extra == 'dev'
Requires-Dist: pytest-asyncio>=0.23.0; extra == 'dev'
Requires-Dist: pytest-mock>=3.12.0; extra == 'dev'
Requires-Dist: pytest>=8.0.0; extra == 'dev'
Requires-Dist: ruff>=0.4.0; extra == 'dev'
